README.md
setup.py
multi_sqs_listener/__init__.py
multi_sqs_listener/_long_polling.py
multi_sqs_listener/_short_polling.py
multi_sqs_listener/config.py
multi_sqs_listener/multi_sqs_listener.py
multi_sqs_listener.egg-info/PKG-INFO
multi_sqs_listener.egg-info/SOURCES.txt
multi_sqs_listener.egg-info/dependency_links.txt
multi_sqs_listener.egg-info/not-zip-safe
multi_sqs_listener.egg-info/requires.txt
multi_sqs_listener.egg-info/top_level.txt