Metadata-Version: 1.0
Name: multi-sqs-listener
Version: 1.0.1
Summary: A Python package to listen in parallel to events coming from multiple AWS SQS queues.
Home-page: https://github.com/fvinas/multi_sqs_listener.git
Author: Fabien Vinas
Author-email: fabien.vinas@gmail.com
License: MIT
Platform: UNKNOWN
